pydig/__init__.py
pydig/query_type.py
pydig/resolver.py
pydig-0.3.0.dist-info/LICENSE
pydig-0.3.0.dist-info/WHEEL
pydig-0.3.0.dist-info/METADATA
pydig-0.3.0.dist-info/RECORD
